__init__.py
auth.py
classes.py
cli.py
client.py
recover.py
sparq.py
usage.py
sparq-0.2.6.dist-info/licenses/LICENSE
sparq-0.2.6.dist-info/METADATA
sparq-0.2.6.dist-info/WHEEL
sparq-0.2.6.dist-info/entry_points.txt
sparq-0.2.6.dist-info/top_level.txt
sparq-0.2.6.dist-info/RECORD
