Metadata-Version: 2.4
Name: sparq
Version: 0.2.6
Summary: Python client for the sparq api - automated degree planning for SJSU students + more
Author-email: Shiven Sheth <shivsbots@gmail.com>
License-Expression: MIT
Project-URL: Homepage, https://github.com/shiventi/sparq
Classifier: Programming Language :: Python :: 3
Classifier: Operating System :: OS Independent
Requires-Python: >=3.8
License-File: LICENSE
Requires-Dist: requests>=2.25.0
Dynamic: license-file
